aliyunsdkpairecservice/__init__.py
aliyunsdkpairecservice/request/__init__.py
aliyunsdkpairecservice/request/v20221213/BackflowFeatureConsistencyCheckJobDataRequest.py
aliyunsdkpairecservice/request/v20221213/CheckInstanceResourcesRequest.py
aliyunsdkpairecservice/request/v20221213/CloneExperimentGroupRequest.py
aliyunsdkpairecservice/request/v20221213/CloneExperimentRequest.py
aliyunsdkpairecservice/request/v20221213/CloneFeatureConsistencyCheckJobConfigRequest.py
aliyunsdkpairecservice/request/v20221213/CloneLaboratoryRequest.py
aliyunsdkpairecservice/request/v20221213/CreateABMetricGroupRequest.py
aliyunsdkpairecservice/request/v20221213/CreateABMetricRequest.py
aliyunsdkpairecservice/request/v20221213/CreateCalculationJobsRequest.py
aliyunsdkpairecservice/request/v20221213/CreateCrowdRequest.py
aliyunsdkpairecservice/request/v20221213/CreateExperimentGroupRequest.py
aliyunsdkpairecservice/request/v20221213/CreateExperimentRequest.py
aliyunsdkpairecservice/request/v20221213/CreateFeatureConsistencyCheckJobConfigRequest.py
aliyunsdkpairecservice/request/v20221213/CreateFeatureConsistencyCheckJobRequest.py
aliyunsdkpairecservice/request/v20221213/CreateInstanceResourceRequest.py
aliyunsdkpairecservice/request/v20221213/CreateLaboratoryRequest.py
aliyunsdkpairecservice/request/v20221213/CreateLayerRequest.py
aliyunsdkpairecservice/request/v20221213/CreateParamRequest.py
aliyunsdkpairecservice/request/v20221213/CreateSceneRequest.py
aliyunsdkpairecservice/request/v20221213/CreateSubCrowdRequest.py
aliyunsdkpairecservice/request/v20221213/CreateTableMetaRequest.py
aliyunsdkpairecservice/request/v20221213/DeleteABMetricGroupRequest.py
aliyunsdkpairecservice/request/v20221213/DeleteABMetricRequest.py
aliyunsdkpairecservice/request/v20221213/DeleteCrowdRequest.py
aliyunsdkpairecservice/request/v20221213/DeleteExperimentGroupRequest.py
aliyunsdkpairecservice/request/v20221213/DeleteExperimentRequest.py
aliyun_python_sdk_pairecservice-1.0.3.dist-info/LICENSE
aliyun_python_sdk_pairecservice-1.0.3.dist-info/METADATA
aliyun_python_sdk_pairecservice-1.0.3.dist-info/WHEEL
aliyun_python_sdk_pairecservice-1.0.3.dist-info/top_level.txt
aliyun_python_sdk_pairecservice-1.0.3.dist-info/RECORD
